{
  "creds": {
    "noiseKey": {
      "private": {
        "type": "Buffer",
        "data": "+Iwrmnyiza7Xu4rdkyh1hVmvAmumG8n68ZemIQPo/2I="
      },
      "public": {
        "type": "Buffer",
        "data": "gBERXhalcua2EuCTmto1YTmtGQddI/VLlKJmn4las3g="
      }
    },
    "signedIdentityKey": {
      "private": {
        "type": "Buffer",
        "data": "+Fb9kL4/0zB1aAjEYQ2U2Ch1+EA8x3uokUgrnLCaTkY="
      },
      "public": {
        "type": "Buffer",
        "data": "aPF4GJ/CRzf4nQ3WA/QxeFGxRe2oM4hkRzcULM3oYQw="
      }
    },
    "signedPreKey": {
      "keyPair": {
        "private": {
          "type": "Buffer",
          "data": "OBPqx6dcmhUc4xTIWLMvbwHqrVcyH7KJ8H63NY/kB0I="
        },
        "public": {
          "type": "Buffer",
          "data": "wyKXp09o1s4JOu6nXDfOjC0yx/M+0ivP+89MsgGkYAs="
        }
      },
      "signature": {
        "type": "Buffer",
        "data": "5GW7EbwHG45/GkcI0Kc/Q+W3CIg19B1SGYscbg1J23GT/wE/x5CyOxg5kQTfDOjIeHjRnZ8bNOhHh28f8EI/AA=="
      },
      "keyId": 1
    },
    "registrationId": 113,
    "advSecretKey": "I3BLXDPGVT7Wy4oOeZu2QS+KXHUXQwOKEiZtGotlEOw=",
    "processedHistoryMessages": [
      {
        "key": {
          "remoteJid": "6283197670126@s.whatsapp.net",
          "fromMe": true,
          "id": "FC147DFB8482C3A7D80EAA32D7C44454"
        },
        "messageTimestamp": 1669608323
      }
    ],
    "nextPreKeyId": 61,
    "firstUnuploadedPreKeyId": 61,
    "accountSettings": {
      "unarchiveChats": false
    },
    "account": {
      "details": "CLPSloUEEPPmkJwGGAE=",
      "accountSignatureKey": "TfROgt2Z/9s7u7LJssIdh0tUOgK1bKCBSPmHyfZ6jxA=",
      "accountSignature": "yGxdLfwk9gJH0UJXbwKvdiuUfa3lBp084cKomF0s6mgUMkJQajcv5KnPXOKzJ7AXQdF6xQ4FI2Jr4KJO1GIODQ==",
      "deviceSignature": "vE2FZ+6VXD6g5S2GxvBhqUu7+1Fc313WikJn4SjTBFxKWPzNEpM9G9Mqhlc7opodke769TFICmvq9Do/chwgCg=="
    },
    "me": {
      "id": "6283197670126:3@s.whatsapp.net",
      "name": "@budi01gaming"
    },
    "signalIdentities": [
      {
        "identifier": {
          "name": "6283197670126:3@s.whatsapp.net",
          "deviceId": 0
        },
        "identifierKey": {
          "type": "Buffer",
          "data": "BU30ToLdmf/bO7uyybLCHYdLVDoCtWyggUj5h8n2eo8Q"
        }
      }
    ],
    "platform": "smba",
    "lastAccountSyncTimestamp": 1669608472,
    "myAppStateKeyId": "AAAAAPGS"
  },
  "keys": {
    "preKeys": {
      "1": null,
      "2": {
        "private": {
          "type": "Buffer",
          "data": "cEFYas8Ob3l9b0IblHaoilsgR0cW0WVTCbUnX5h5SEY="
        },
        "public": {
          "type": "Buffer",
          "data": "NIwFkScr7riaeJq2EiY2YfE6kcXjuuGgKHNzAWp2fRY="
        }
      },
      "3": null,
      "4": null,
      "5": {
        "private": {
          "type": "Buffer",
          "data": "SGANFqT+vsFy5EVfRKP2zMwVfR6viNMGlfgTJ201nHU="
        },
        "public": {
          "type": "Buffer",
          "data": "a1CGLO2ihI8pV8Z+BBEjL78MZ7gG1r4/5shGNmiuzX0="
        }
      },
      "6": {
        "private": {
          "type": "Buffer",
          "data": "8JfBqICpe++GfAv9CVx6SFyL+F+wsj55c3WWCcVEWUE="
        },
        "public": {
          "type": "Buffer",
          "data": "HunaKrbdej3RyVri43BHZEW2j2MngnfRyadjprHmITM="
        }
      },
      "7": null,
      "8": {
        "private": {
          "type": "Buffer",
          "data": "UIAwmev9swgnfZ6S8CrSDDfsReQX4K1DkXL3Jd3THkc="
        },
        "public": {
          "type": "Buffer",
          "data": "4GZ2pYkVvDzd9nLfcKsdi5FZb+jyS4SLcjRqSnRTMm8="
        }
      },
      "9": null,
      "10": null,
      "11": null,
      "12": {
        "private": {
          "type": "Buffer",
          "data": "cIqgA8X1TTQaMM5YDcW+tYvGTF8EZBv0BFJoeZ1+W2w="
        },
        "public": {
          "type": "Buffer",
          "data": "ho+MIlm6bEBeoVmkY2vQ6Q/BedVTKl5hEgBpbNk4J3g="
        }
      },
      "13": {
        "private": {
          "type": "Buffer",
          "data": "CIo1nIjdsCOIpZEU2r8j9hvrKCiVxQRdLaMotqTFbHs="
        },
        "public": {
          "type": "Buffer",
          "data": "7ma9gkx6yJkrgC5/3wAWFv6u5kHkcXAtDOMdgE9iHyI="
        }
      },
      "14": {
        "private": {
          "type": "Buffer",
          "data": "6GjPXyEWu2aX0r0r7xnDGnDHirWAnH4piPsrDzEoKVY="
        },
        "public": {
          "type": "Buffer",
          "data": "zSUuX5CRMdMSKy8p1kqMMwo2DVhJZQq8z38lTgJIhz0="
        }
      },
      "15": {
        "private": {
          "type": "Buffer",
          "data": "yPCo+n1ne418/OgCQ3ONYWr4VO0MTCRl8A59w7qwfkU="
        },
        "public": {
          "type": "Buffer",
          "data": "nL6hbW5WmobYX6mNWGArfEZjzcy3R0A5kE1e8fLI7EA="
        }
      },
      "16": null,
      "17": {
        "private": {
          "type": "Buffer",
          "data": "QCMy81mUQyJwpn8zJkH6Jo18LRVPNohmmf1hHxiylWw="
        },
        "public": {
          "type": "Buffer",
          "data": "/6eOrkKlT9VHiKXpnxH3rcSPrS5JwLhXsxQObKsNuCM="
        }
      },
      "18": null,
      "19": null,
      "20": {
        "private": {
          "type": "Buffer",
          "data": "wBPAx2n3GY8cQza8BPTy32bWaVonXP3H4N14y1+WIX0="
        },
        "public": {
          "type": "Buffer",
          "data": "k3JVdtHjnZryblIlOcnXggVaBerqWdIahmtH/n6420c="
        }
      },
      "21": null,
      "22": null,
      "23": {
        "private": {
          "type": "Buffer",
          "data": "2CK3F25iLeeVkSPYF5MyjeVlr3pd97Yk5BcT/41WaUI="
        },
        "public": {
          "type": "Buffer",
          "data": "jpuad3LeGkzKIT7cKpa9eMTd7BNIlj9H3cMdEYIKUCY="
        }
      },
      "24": null,
      "25": null,
      "26": null,
      "27": null,
      "28": {
        "private": {
          "type": "Buffer",
          "data": "ILeNxFdct5r9WzErPWZrHqovXbhqWddehaYTD4UdQFw="
        },
        "public": {
          "type": "Buffer",
          "data": "vJC0tgtTO9R1s08h1IW7UhmOSSoUli197zlAew5n6UQ="
        }
      },
      "29": null,
      "30": null,
      "31": {
        "private": {
          "type": "Buffer",
          "data": "IMbnsGQiYn2KHFlk6STwSPXRfunbVQEwHSQpyJA300I="
        },
        "public": {
          "type": "Buffer",
          "data": "N2cD/MbSQEXB0X0vXremgqHCay+RQ6CoVQgVvMda4Qw="
        }
      },
      "32": {
        "private": {
          "type": "Buffer",
          "data": "6MRQOU4HmwUZO1/JlouHtPuMIn7H4uhnJqODSoyGB2M="
        },
        "public": {
          "type": "Buffer",
          "data": "6VYKJDoDtJ7IsksV03RewXSNIgaWfOPVcgrxgbJzgy4="
        }
      },
      "33": {
        "private": {
          "type": "Buffer",
          "data": "mPDvv73Z7dMbgaLrfWdReF3MbgtF0jA4gvv5wzncJUU="
        },
        "public": {
          "type": "Buffer",
          "data": "MCzzySuVOziJxNnan5yIoPZekeyYyVEjkVg3yF5KxD4="
        }
      },
      "34": {
        "private": {
          "type": "Buffer",
          "data": "YO7pxEZEpr+bw9+dc/avxdpezt/RLxrv13gmGTxKcXI="
        },
        "public": {
          "type": "Buffer",
          "data": "4ulFckD3RjXNNTDkQWflEAfhjJv5YmHBv3pedj5kaD0="
        }
      },
      "35": {
        "private": {
          "type": "Buffer",
          "data": "SJuG69UQMzQpF3qzjitEIGdb1ebi7gTjdUsJEmp0v28="
        },
        "public": {
          "type": "Buffer",
          "data": "n+32cKAiqfRxu8KRncPhPr2licsOnePmHOX9zBuS/hw="
        }
      },
      "36": {
        "private": {
          "type": "Buffer",
          "data": "GO3A9MOMfF6iNEoe1hJ+tUnBBRG/QSTV20rCQlGL9FM="
        },
        "public": {
          "type": "Buffer",
          "data": "BVnSd9hx/VbnEBcxsr7QK/9msSfB8iALBqS6iE22Uxk="
        }
      },
      "37": {
        "private": {
          "type": "Buffer",
          "data": "mE4kD2DeWo4F6UoZqjnaXYrj+JiPgzZkr8f09Vl9m2M="
        },
        "public": {
          "type": "Buffer",
          "data": "u15JJBF9On2dA63aU05I8EQVMEY8sKjlUJ+PpbhnPA4="
        }
      },
      "38": {
        "private": {
          "type": "Buffer",
          "data": "QG22Q2tmxDQqTCl5+eIJQx/1gG/H1749fSEC6xvq0nw="
        },
        "public": {
          "type": "Buffer",
          "data": "sfV457L+RRxtWIp01ajG9LGisTw+dokNVUA6bqo6Ym0="
        }
      },
      "39": {
        "private": {
          "type": "Buffer",
          "data": "EDxSw5hWHBfy4KXvVVyHhJrKGvmsqIg+HWBk1qpHamU="
        },
        "public": {
          "type": "Buffer",
          "data": "T+qlDcr83mdfSzgfx/oUELAqa0JY1jPmsfYiz+2O2RI="
        }
      },
      "40": {
        "private": {
          "type": "Buffer",
          "data": "iH4U+ppZqrNoyoQhqITDqN+k+lroMfHQqzbLR9SbDGc="
        },
        "public": {
          "type": "Buffer",
          "data": "Z/168gmWqpI/FW2IHSkKR9sywPEsuxd5imYfY6qFTkQ="
        }
      },
      "41": {
        "private": {
          "type": "Buffer",
          "data": "gEn4D5SZBk3t4Ui9KSI6j/GDlHPjT1Y/06DJhAEDEn0="
        },
        "public": {
          "type": "Buffer",
          "data": "yyRbSIBdxYb5HjW8UL63+HgIScEeLWBnnrTpyEoQNzk="
        }
      },
      "42": {
        "private": {
          "type": "Buffer",
          "data": "2NLVLuALBY9N1mzKiKTxQGTAPtXB82xqIPdb/jQJm2A="
        },
        "public": {
          "type": "Buffer",
          "data": "9XUowNOHsTq3SYa0ioEdLZgbfOoB7sgxx0ixzPtWkgs="
        }
      },
      "43": {
        "private": {
          "type": "Buffer",
          "data": "gBAxFyMpvML25J8K0g3L72T/PkPuvIZ30Tngw/2OOWI="
        },
        "public": {
          "type": "Buffer",
          "data": "/99mIu5DPpkTxZ8dSM6OnuNbN0JL4MafJIXFPgyh/y4="
        }
      },
      "44": {
        "private": {
          "type": "Buffer",
          "data": "wILo1nuBdymAVYsDWU9esN96tc44VV8j9TaOdP59MF8="
        },
        "public": {
          "type": "Buffer",
          "data": "69c5FNS5/91P9m1HGz5Gy4W5sXA9ZPYpFSnV8rVsbQI="
        }
      },
      "45": {
        "private": {
          "type": "Buffer",
          "data": "OFbTuQRB0xTX4mPQUP7Fp7MFNm30CXsOttP2HJYJbEA="
        },
        "public": {
          "type": "Buffer",
          "data": "BJ0cfPK+6sQUrIT4v+FNiiQj5s3kb2lbB7hox7viLzc="
        }
      },
      "46": null,
      "47": {
        "private": {
          "type": "Buffer",
          "data": "KCEP+mVgTiF+m1fXMFX01LxHoA2LRK195nJ/omky9nk="
        },
        "public": {
          "type": "Buffer",
          "data": "lD5xLT2uUqTn5VUqhPDBshmlTN65OBks3tho7o3a8lw="
        }
      },
      "48": {
        "private": {
          "type": "Buffer",
          "data": "ELEXuB3yru/N5KwZh5RqEuBiR0BB73aCyZB4t9roV1Q="
        },
        "public": {
          "type": "Buffer",
          "data": "pUinFvBX9gUk2YY31MVNShC8S0XqgkjMXgJ8ArBMKAo="
        }
      },
      "49": {
        "private": {
          "type": "Buffer",
          "data": "ICqbUjRpWZ16xZeBQJFADeUvsy+b1SoRoBKD49PC90o="
        },
        "public": {
          "type": "Buffer",
          "data": "i/J5HE/huDDXErNrpwxhdsJv0hMWaCpnf9QTX0IYxQQ="
        }
      },
      "50": {
        "private": {
          "type": "Buffer",
          "data": "cNTyWGoOqMJyDctnQQa4ale81tnV7XZ8xJ4295DNkkI="
        },
        "public": {
          "type": "Buffer",
          "data": "q55H/yfU8wv4MAu5n8OiJQC1WR/7MHZcGkzJyVQ2MXI="
        }
      },
      "51": {
        "private": {
          "type": "Buffer",
          "data": "WM9N22pPGu6XYxj26ya71/P6NkUGeSg3s1bAgfIw2WQ="
        },
        "public": {
          "type": "Buffer",
          "data": "nMaaSkatl1mVFPBRhPGU09j8KZx//7pxrz4IZn+pJmM="
        }
      },
      "52": {
        "private": {
          "type": "Buffer",
          "data": "AJNW8eQoQdISi7GmVZQGT6Q6VGKjH+SyKi2u/qzDKmc="
        },
        "public": {
          "type": "Buffer",
          "data": "lZiXOruFAwubn9HFLFcegeycwXYpdC/7sl83u1kVU1A="
        }
      },
      "53": {
        "private": {
          "type": "Buffer",
          "data": "oNXWTvvBvqSkf/o1wZmoSrU+eAX4C+qMya+3T75Uz0Q="
        },
        "public": {
          "type": "Buffer",
          "data": "Sc0QY5u6ZpyNcS1bwutKO0UyytYtS9k2FQDXNOvvEwU="
        }
      },
      "54": {
        "private": {
          "type": "Buffer",
          "data": "uBTs5gWlrgkr0oFH5yo5bwWVuAGmMnYa5LOBDwhNOEQ="
        },
        "public": {
          "type": "Buffer",
          "data": "EQ8RsYetgZsATxhzrSKx0nK9lo13u/KLmMsF8JyMJ0s="
        }
      },
      "55": {
        "private": {
          "type": "Buffer",
          "data": "KOPFSAPGXHkT9Vl/iT6MI9KYvBlsYW46YxT3BpZtZEQ="
        },
        "public": {
          "type": "Buffer",
          "data": "ZaAEsWbaj/rLp/Y+LZcreHRG0axTlD3GHPLVhzmi2Do="
        }
      },
      "56": {
        "private": {
          "type": "Buffer",
          "data": "aMeZwS+MgU6tEpyyh7H+PaAoYmQiAIyIvLXU+nQ5OE8="
        },
        "public": {
          "type": "Buffer",
          "data": "6OIIe7XgI+cuxrxKvfPkjbjbJ8JuK0xZaVjVoIWb5XI="
        }
      },
      "57": {
        "private": {
          "type": "Buffer",
          "data": "uPMP/Jjquq4MPgH4AcGwZBhD0cm7ndiPPZ9Mkvfqe2w="
        },
        "public": {
          "type": "Buffer",
          "data": "edW50p9k30toWVUZMzXABgTlGIdNdAaIBV3R7geKzCs="
        }
      },
      "58": {
        "private": {
          "type": "Buffer",
          "data": "QPaDVRhmpys5S4qVvSEOKo5p0BtmGSe/M7f+8wJS/Vk="
        },
        "public": {
          "type": "Buffer",
          "data": "dZVxLmmLw2WHKnggVl1/SYU93rnYm9+jgvtx0415XDg="
        }
      },
      "59": {
        "private": {
          "type": "Buffer",
          "data": "aL3gMpBfMeY736chheSwrtxHlIwMBuQgAKs1COqCDmA="
        },
        "public": {
          "type": "Buffer",
          "data": "1TGGlvLfacZFcoO9xIeOPUTvRvgN3LVeV8/Jj3ZtUBU="
        }
      },
      "60": {
        "private": {
          "type": "Buffer",
          "data": "+NjDNaLvZTzu3HL8CPEEBuIRpA1yYPN28eQzFr6+mFk="
        },
        "public": {
          "type": "Buffer",
          "data": "Yu+HxTr0raPoVwnsO+DlZx0I2QxsTIqe7Y+/2GQv9zA="
        }
      }
    },
    "sessions": {
      "6283197670126.0": {
        "_sessions": {
          "BTKu1LpUB/asAM1kW2JekyZYhLSANU+Gs3bNwWRDE7gD": {
            "registrationId": 2007596647,
            "currentRatchet": {
              "ephemeralKeyPair": {
                "pubKey": "BdyUd4VUh5d2FdENgqLFGYtvcuHpDM1n8Nmo3mxVzgtj",
                "privKey": "MIdQRAXqd60II1pW+nW9YWcPkFEDHE74IUzu9XM4Als="
              },
              "lastRemoteEphemeralKey": "BbFTyZJqUaiVOK5WQU2bMbpFyF952VUSEuU7872+7Ysc",
              "previousCounter": 9,
              "rootKey": "GYv2KvZdLODQmJF6FXNT8X4ryTR/qKzIQY7C9K8NdVI="
            },
            "indexInfo": {
              "baseKey": "BTKu1LpUB/asAM1kW2JekyZYhLSANU+Gs3bNwWRDE7gD",
              "baseKeyType": 2,
              "closed": -1,
              "used": 1669609265113,
              "created": 1669608312299,
              "remoteIdentityKey": "BU30ToLdmf/bO7uyybLCHYdLVDoCtWyggUj5h8n2eo8Q"
            },
            "_chains": {
              "Bew/ruK6dZ/tJEFWBmtvItxLVOGdTcZd4DSdv71iGyF4": {
                "chainKey": {
                  "counter": 5
                },
                "chainType": 2,
                "messageKeys": {}
              },
              "BbFTyZJqUaiVOK5WQU2bMbpFyF952VUSEuU7872+7Ysc": {
                "chainKey": {
                  "counter": 0,
                  "key": "S2yGMC1DgTp6lELEuhFoLjuBIfdyYVkDmb8I5+vNnqE="
                },
                "chainType": 2,
                "messageKeys": {}
              },
              "BdyUd4VUh5d2FdENgqLFGYtvcuHpDM1n8Nmo3mxVzgtj": {
                "chainKey": {
                  "counter": 5,
                  "key": "o/7cANOWid8VZzkhMx1YJ2SNTciG3CC89mYbgn/+mDM="
                },
                "chainType": 1,
                "messageKeys": {}
              }
            }
          }
        },
        "version": "v1"
      },
      "6285215319934.0": {
        "_sessions": {
          "BXh0063pAKq5BrcRswWrFmRDL5ETDgMrNiniEi+ukutu": {
            "registrationId": 750863683,
            "currentRatchet": {
              "ephemeralKeyPair": {
                "pubKey": "BcqZCE2RMtMOa2j7LDf+aBITXSqUopv3iOjtx66eC6Y2",
                "privKey": "OAhF+pIDB7T9sZx/YSTSGriS+WnpLTX75r0Dn3n813Y="
              },
              "lastRemoteEphemeralKey": "BcE0DA2JM2GCt4dPB8jV0JBGIXOM/msP3Kx4JcXCZpJ+",
              "previousCounter": 0,
              "rootKey": "sgf12EooPboG3q6lAi+iuIihtHupAjBEJbctJS7H1DY="
            },
            "indexInfo": {
              "baseKey": "BXh0063pAKq5BrcRswWrFmRDL5ETDgMrNiniEi+ukutu",
              "baseKeyType": 2,
              "closed": -1,
              "used": 1669610700302,
              "created": 1669608362171,
              "remoteIdentityKey": "Baz1L5OM3g40lx8kdsY+nMhAgGSsa9W383gNJ/zcqPoe"
            },
            "_chains": {
              "BWPgSJ5KmumjYtm5dS6QX1RrLeUeJzVQZLsf1ts0rA15": {
                "chainKey": {
                  "counter": 7
                },
                "chainType": 2,
                "messageKeys": {}
              },
              "BRPtxG8ypi5rx/EP0S0kQvjwhkdamm7UrtIysG0AO4hj": {
                "chainKey": {
                  "counter": 1
                },
                "chainType": 2,
                "messageKeys": {}
              },
              "Bcq20z7pqIvg2VKv98wXzEnyQL6LHKuAeYj9Tspy73kV": {
                "chainKey": {
                  "counter": 0
                },
                "chainType": 2,
                "messageKeys": {}
              },
              "BZd48BLU05+Bi8Q2biIFrrOBzR1SQyoRbZKQQol2G2IJ": {
                "chainKey": {
                  "counter": 0
                },
                "chainType": 2,
                "messageKeys": {}
              },
              "BezDFKmFqbBkW92rk6WmD22/qvQ5RIJ/SGioftuI6L9+": {
                "chainKey": {
                  "counter": 0
                },
                "chainType": 2,
                "messageKeys": {}
              },
              "BQk00Qdx56P3gqN6xJTdngMLe4f2K/6+EIeGYAUiyR9T": {
                "chainKey": {
                  "counter": 3
                },
                "chainType": 2,
                "messageKeys": {
                  "1": "GQge9kXM4YHuEV6f8KkKq0Wic684rZQR0WZYREY3xKQ="
                }
              },
              "BS9F+4Dqr82ic/u6EW5A0gdCKk1cTepaJw+x9oACr/xC": {
                "chainKey": {
                  "counter": 0
                },
                "chainType": 2,
                "messageKeys": {}
              },
              "BfH/g0tPG0C7+pSbIw+UsLqWi4kJ19fZ5ZxLJfXBroJQ": {
                "chainKey": {
                  "counter": 0
                },
                "chainType": 2,
                "messageKeys": {}
              },
              "BZ7SPuAGVLxlDLsHLbUJJNX2u6OEtcGSBoYKlWTwXgkf": {
                "chainKey": {
                  "counter": 0
                },
                "chainType": 2,
                "messageKeys": {}
              },
              "BSC026VcZkQPsodKx25PXOfj1/Q8qBBCQ9EZ7TpnT+MD": {
                "chainKey": {
                  "counter": 0
                },
                "chainType": 2,
                "messageKeys": {}
              },
              "BcE0DA2JM2GCt4dPB8jV0JBGIXOM/msP3Kx4JcXCZpJ+": {
                "chainKey": {
                  "counter": 0,
                  "key": "SluZaLxgkArdcQ6cZEKmooA0xv2cpGOdYjbgJbQvga8="
                },
                "chainType": 2,
                "messageKeys": {}
              },
              "BcqZCE2RMtMOa2j7LDf+aBITXSqUopv3iOjtx66eC6Y2": {
                "chainKey": {
                  "counter": -1,
                  "key": "dSx4AV1oViBd34gdr4kUsXQ78ndFTdOCTXlMQTa93Wg="
                },
                "chainType": 1,
                "messageKeys": {}
              }
            }
          }
        },
        "version": "v1"
      },
      "6281253874123.0": {
        "_sessions": {
          "Be+eJWu/NjiyHxZboy2paOaTivxJu9weH5LB5Dn3n9Zw": {
            "registrationId": 287036435,
            "currentRatchet": {
              "ephemeralKeyPair": {
                "pubKey": "BSLQ8HLuRYkOrT5EybqjwW33whv788Tl+WavXWQWoSF+",
                "privKey": "+O9zh2m+ifcRrzOV/OMrnEoMpCAd1ziUa8yh6FMek30="
              },
              "lastRemoteEphemeralKey": "BYQCmQOWol5VuRazUOkxo1GOKqibWOtFei3htkrFUhJ9",
              "previousCounter": 0,
              "rootKey": "rr4JMvLlar2hnjfx1W14DODHoXngdqWjhpNIzjRDGJY="
            },
            "indexInfo": {
              "baseKey": "Be+eJWu/NjiyHxZboy2paOaTivxJu9weH5LB5Dn3n9Zw",
              "baseKeyType": 2,
              "closed": -1,
              "used": 1669608406424,
              "created": 1669608406424,
              "remoteIdentityKey": "BZq/pO3eFUA2GBVQOOwAjxOq1zEowXKJXaDSO6JLX/4d"
            },
            "_chains": {
              "BYQCmQOWol5VuRazUOkxo1GOKqibWOtFei3htkrFUhJ9": {
                "chainKey": {
                  "counter": 0,
                  "key": "TD3uSSmJpxE2z96+ZsyoFCV7eDBGj3EwVyu4fLTR38Q="
                },
                "chainType": 2,
                "messageKeys": {}
              },
              "BSLQ8HLuRYkOrT5EybqjwW33whv788Tl+WavXWQWoSF+": {
                "chainKey": {
                  "counter": -1,
                  "key": "/ww4a3ZOxdfY7QvE3E7a1NSMFDKWOkN0q/yGcAQ82nY="
                },
                "chainType": 1,
                "messageKeys": {}
              }
            }
          }
        },
        "version": "v1"
      },
      "6285735868941.0": {
        "_sessions": {
          "BcGRqFTd2dawDw9wVjcvhA8aD2PoOdbS9uO9ORka5Np5": {
            "registrationId": 1122804108,
            "currentRatchet": {
              "ephemeralKeyPair": {
                "pubKey": "BTSYRRFBC+is0eybedKwToMJlX72a2GYAO6rJI+oneFt",
                "privKey": "EP1rWPPnIr3uEvqCypyOlBoe4zibyJWHp+swpyXDpko="
              },
              "lastRemoteEphemeralKey": "BSuEnP3aOl8lwpIk4rYLjKDrn5afRVyFrEGMocREHEZj",
              "previousCounter": 0,
              "rootKey": "0lxeQoSo2FF4fHdur2Mru53xzbk3RwvPq1zHwAlhKIs="
            },
            "indexInfo": {
              "baseKey": "BcGRqFTd2dawDw9wVjcvhA8aD2PoOdbS9uO9ORka5Np5",
              "baseKeyType": 2,
              "closed": -1,
              "used": 1669608487386,
              "created": 1669608487386,
              "remoteIdentityKey": "BZLfPqh9XLw9pyy+EVVj/DgGAJCQKQI/1hK422e9z8U/"
            },
            "_chains": {
              "BSuEnP3aOl8lwpIk4rYLjKDrn5afRVyFrEGMocREHEZj": {
                "chainKey": {
                  "counter": 2,
                  "key": "d4P02+WdDaGLoVddu7qjDDm/Ns2YPL/fl5XXBm9tCFA="
                },
                "chainType": 2,
                "messageKeys": {}
              },
              "BTSYRRFBC+is0eybedKwToMJlX72a2GYAO6rJI+oneFt": {
                "chainKey": {
                  "counter": -1,
                  "key": "dtqqhmYAcLfYHm0YBokc+WgdW/bsjUDhP3HeyZqy+EE="
                },
                "chainType": 1,
                "messageKeys": {}
              }
            }
          }
        },
        "version": "v1"
      },
      "6283149289769.0": {
        "_sessions": {
          "BRmZZG2fz078+0+NTn3/kzSNNijv9Ig7T89gfufgEIA1": {
            "registrationId": 1194943574,
            "currentRatchet": {
              "ephemeralKeyPair": {
                "pubKey": "BRLPXDIqGoSlAIDeHTNnqKas1I0LAARbtR0Bq4siX69L",
                "privKey": "QGWyuZJ+77AYbGrlvOx7vj441EEx/D2tU1JyFnReYnY="
              },
              "lastRemoteEphemeralKey": "BZZsJb1kJlKRqsqRxgH5IdDsmxvr7ZFANJNcdT12D1AH",
              "previousCounter": 0,
              "rootKey": "Lsvagdztm+2sTsLjqGxbkycco6zbMC/ywOMauHJyybw="
            },
            "indexInfo": {
              "baseKey": "BRmZZG2fz078+0+NTn3/kzSNNijv9Ig7T89gfufgEIA1",
              "baseKeyType": 2,
              "closed": -1,
              "used": 1669608795888,
              "created": 1669608795888,
              "remoteIdentityKey": "BaYQElQMo4oj88NzQdJJ9xHIN1UYDLTYOLJN+NhEH/ca"
            },
            "_chains": {
              "BZZsJb1kJlKRqsqRxgH5IdDsmxvr7ZFANJNcdT12D1AH": {
                "chainKey": {
                  "counter": 0,
                  "key": "0T+plDeEuSrDAFUiuGfSO/z2Em0KrmurEs8yKBx4Ed8="
                },
                "chainType": 2,
                "messageKeys": {}
              },
              "BRLPXDIqGoSlAIDeHTNnqKas1I0LAARbtR0Bq4siX69L": {
                "chainKey": {
                  "counter": -1,
                  "key": "hCG7QQMT1+t511yE0esfq4dd/XvSBd4CMstvDGvTA2I="
                },
                "chainType": 1,
                "messageKeys": {}
              }
            }
          }
        },
        "version": "v1"
      },
      "6283863467345.0": {
        "_sessions": {
          "BXrdh7YhmJ+8W1oM2EOBa0c8mNV0LCoXfhuhige/I8BC": {
            "registrationId": 1780832045,
            "currentRatchet": {
              "ephemeralKeyPair": {
                "pubKey": "BaKwEb9FbwqpCko77ZCyjLGgfFMFrEJb9OELHNP90QMQ",
                "privKey": "0J77DDUhC6zEfQ9501TJC/sYqIERaO0LKCeSyz4T/04="
              },
              "lastRemoteEphemeralKey": "BbtBpLJZ/dVCnZEqE7GVvzL1pu3ECIq5X99LnKVShfRk",
              "previousCounter": 0,
              "rootKey": "etezSMlxj3QRz01Ljl+PGAu0exEUF6c+jJuWx+HTMNI="
            },
            "indexInfo": {
              "baseKey": "BXrdh7YhmJ+8W1oM2EOBa0c8mNV0LCoXfhuhige/I8BC",
              "baseKeyType": 2,
              "closed": -1,
              "used": 1669608796040,
              "created": 1669608796040,
              "remoteIdentityKey": "BawxD+B1yxvWdOns3hlZPceWjOBifaQLAdE0I81IyXJv"
            },
            "_chains": {
              "BbtBpLJZ/dVCnZEqE7GVvzL1pu3ECIq5X99LnKVShfRk": {
                "chainKey": {
                  "counter": 0,
                  "key": "Ir8/hGT6bw8DqmEHQ5xwaabOOAa0lA9ltvkyRfXd+7U="
                },
                "chainType": 2,
                "messageKeys": {}
              },
              "BaKwEb9FbwqpCko77ZCyjLGgfFMFrEJb9OELHNP90QMQ": {
                "chainKey": {
                  "counter": -1,
                  "key": "UUyUMSEiu2B3LrRGx367VWNW/Vorzk1ogreDrlDxGNs="
                },
                "chainType": 1,
                "messageKeys": {}
              }
            }
          }
        },
        "version": "v1"
      },
      "6282251331001.0": {
        "_sessions": {
          "BdPfNK9HOGOTg1tSH7KOh//6kM05DG4/E+BgP5WFN+tP": {
            "registrationId": 1106465037,
            "currentRatchet": {
              "ephemeralKeyPair": {
                "pubKey": "BSSaTuHtFnvhhsByL8kaKmQYBahyHni6D5Tw28ICK2hF",
                "privKey": "+PE3zr+7WcnrOchDC+axRhfsEinKK4D61JJ+hcf8Rmo="
              },
              "lastRemoteEphemeralKey": "BVAh808aStWtinp4Th0TCzoqORZQrNXGT1bcnJKBhslb",
              "previousCounter": 0,
              "rootKey": "yBk9sHWKI/zHyNWj2K7oWZauujbP4VJZlFwUSe9hzc0="
            },
            "indexInfo": {
              "baseKey": "BdPfNK9HOGOTg1tSH7KOh//6kM05DG4/E+BgP5WFN+tP",
              "baseKeyType": 2,
              "closed": -1,
              "used": 1669608852724,
              "created": 1669608852724,
              "remoteIdentityKey": "BbupeZlF6kHz/+9d4PIYe9LZsZC5YTS7Aw01gOD812VL"
            },
            "_chains": {
              "BVAh808aStWtinp4Th0TCzoqORZQrNXGT1bcnJKBhslb": {
                "chainKey": {
                  "counter": 2,
                  "key": "A9fjlusyCayCngNBcjRhC/pAYb4mYktfrOlwzvds+Aw="
                },
                "chainType": 2,
                "messageKeys": {}
              },
              "BSSaTuHtFnvhhsByL8kaKmQYBahyHni6D5Tw28ICK2hF": {
                "chainKey": {
                  "counter": -1,
                  "key": "XQS7bJLZxXtEeQ+0OmVbytULrajyn15LgAwNGnnzMMY="
                },
                "chainType": 1,
                "messageKeys": {}
              }
            }
          }
        },
        "version": "v1"
      },
      "6281563167690.0": {
        "_sessions": {
          "BVz1bZQ8GY5wTmTvQtb1IGbjDIqahw8LJW7l/Bv1Txhe": {
            "registrationId": 1411286343,
            "currentRatchet": {
              "ephemeralKeyPair": {
                "pubKey": "Bfg+AxxFEL///Twa614arELypRpuXwhjYFTy2GqnlAs6",
                "privKey": "YPBSFHn4m9+dc2lNYSaT+xIrHW06HslS0AnDPRWd5Hk="
              },
              "lastRemoteEphemeralKey": "BWRwiuk7t48nSXgGfd+3ha6WrtbmFK/PlK6gocEJ3+RM",
              "previousCounter": 0,
              "rootKey": "Z+HFufAyA+rfckGot2+JUaBd39xDIosJIs2madgq94k="
            },
            "indexInfo": {
              "baseKey": "BVz1bZQ8GY5wTmTvQtb1IGbjDIqahw8LJW7l/Bv1Txhe",
              "baseKeyType": 2,
              "closed": -1,
              "used": 1669608853983,
              "created": 1669608853983,
              "remoteIdentityKey": "BbIpDVf3JhODP0vcDiL434R6IoEEyLFxyvGPNWbQLFte"
            },
            "_chains": {
              "BWRwiuk7t48nSXgGfd+3ha6WrtbmFK/PlK6gocEJ3+RM": {
                "chainKey": {
                  "counter": 2,
                  "key": "2C+Ev6bqWUdesIYsQOX1+/NtmJT6pl8odk9oYrRGCnk="
                },
                "chainType": 2,
                "messageKeys": {
                  "0": "6B0TWikE5/AT0iVWsOY9b8AF+T9zAk0GWNTM9JU6g54="
                }
              },
              "Bfg+AxxFEL///Twa614arELypRpuXwhjYFTy2GqnlAs6": {
                "chainKey": {
                  "counter": -1,
                  "key": "dMwJJ2YFvbHjR+/S+QcFyNhkJ6slAg90yZxRU4xxp5I="
                },
                "chainType": 1,
                "messageKeys": {}
              }
            }
          }
        },
        "version": "v1"
      },
      "6281220590183.0": {
        "_sessions": {
          "BW7bCCiWiZ1qQTVTBDv47/Kk8cBPOKLs8AqePrpcTnh8": {
            "registrationId": 1671701886,
            "currentRatchet": {
              "ephemeralKeyPair": {
                "pubKey": "BVVXKT47PB2753+CeALn9QIk2WYjPGPVILyo1OUIe1RZ",
                "privKey": "iN1Th5wZk7Afeni2V28i1vxcuBNROYiqnCaDME+Hn1k="
              },
              "lastRemoteEphemeralKey": "BemiyOyKRL1ZCvS8bqsKgSkiYNcD8C1NBd04Z53o9K8x",
              "previousCounter": 0,
              "rootKey": "l/kxHryl9OY3eOM5T3UFWHW7LJ2HGL8J8+TolbHN8Tc="
            },
            "indexInfo": {
              "baseKey": "BW7bCCiWiZ1qQTVTBDv47/Kk8cBPOKLs8AqePrpcTnh8",
              "baseKeyType": 2,
              "closed": -1,
              "used": 1669608994930,
              "created": 1669608994930,
              "remoteIdentityKey": "BS5M0O1oQ5MOmvpgWKZNnLqqrzJoEmcvZe4JLsbedYYQ"
            },
            "_chains": {
              "BemiyOyKRL1ZCvS8bqsKgSkiYNcD8C1NBd04Z53o9K8x": {
                "chainKey": {
                  "counter": 0,
                  "key": "YOwK2HgldxZ5nq+BbopcWhXYauDMp1gSvzFmwJlcZEA="
                },
                "chainType": 2,
                "messageKeys": {}
              },
              "BVVXKT47PB2753+CeALn9QIk2WYjPGPVILyo1OUIe1RZ": {
                "chainKey": {
                  "counter": -1,
                  "key": "W0SEP/7O4lFL/LFWw/hwZKiOd+PJHwXYVZXvpA825J8="
                },
                "chainType": 1,
                "messageKeys": {}
              }
            }
          }
        },
        "version": "v1"
      },
      "6283151524041.0": {
        "_sessions": {
          "BZHsmP9JcOLlYxGpJYTfZA9znuC9F65aE1KtwFlQCopm": {
            "registrationId": 1314249883,
            "currentRatchet": {
              "ephemeralKeyPair": {
                "pubKey": "BQT6gRAVI4cTzzgVIG2SsdO0sDKimcjTK+dmRxwzidVP",
                "privKey": "8LCvyEcYNVWEjFKaf5h56PQ6d/DwIGvBt5IDhJW5lV8="
              },
              "lastRemoteEphemeralKey": "BbXBD5r92EiOb8fX1bGmMKrgBFXV79HAGkO3yo/2fU4e",
              "previousCounter": 0,
              "rootKey": "CK5ivA05V3tUDvkkXV7Czx0EIksx+b1ktvWhMHapgKM="
            },
            "indexInfo": {
              "baseKey": "BZHsmP9JcOLlYxGpJYTfZA9znuC9F65aE1KtwFlQCopm",
              "baseKeyType": 2,
              "closed": -1,
              "used": 1669609053975,
              "created": 1669609053975,
              "remoteIdentityKey": "BRkoxCKrYQdGhPRybHC0Z9M7ahyckdCaINHqhaD4ELhL"
            },
            "_chains": {
              "BbXBD5r92EiOb8fX1bGmMKrgBFXV79HAGkO3yo/2fU4e": {
                "chainKey": {
                  "counter": 0,
                  "key": "+1vZcR+QiaJVDGsj/oyfy+513gnTg3HHk3Pfd7LTnXA="
                },
                "chainType": 2,
                "messageKeys": {}
              },
              "BQT6gRAVI4cTzzgVIG2SsdO0sDKimcjTK+dmRxwzidVP": {
                "chainKey": {
                  "counter": -1,
                  "key": "Ni4aQjpD+xNQRWhnzScE1oo1LT8H5VuUUuhm9LuOPfo="
                },
                "chainType": 1,
                "messageKeys": {}
              }
            }
          }
        },
        "version": "v1"
      },
      "6285940752001.0": {
        "_sessions": {
          "BYGlxMdmTt4DZS3vKzm7Iw8Vz9lYBMW6DyB3mvpva1A3": {
            "registrationId": 1801282322,
            "currentRatchet": {
              "ephemeralKeyPair": {
                "pubKey": "BfTiguoDvbb3I6CrLJo+aOtoFLIFsRs8k3Ii/t6Fk2la",
                "privKey": "oEfgnX5hdrIX6VByxYIBBkUIFN6yjSXg11aL7hz34GA="
              },
              "lastRemoteEphemeralKey": "BSfkp8QbwgKhGtz1dSkDCyL1TETNPQgckRMRCvtPpSpN",
              "previousCounter": 0,
              "rootKey": "WYYNWeLhi3apoeeTrOOMlTT4tMkWux6mbg+j+ww3LcU="
            },
            "indexInfo": {
              "baseKey": "BYGlxMdmTt4DZS3vKzm7Iw8Vz9lYBMW6DyB3mvpva1A3",
              "baseKeyType": 2,
              "closed": -1,
              "used": 1669609274350,
              "created": 1669609274350,
              "remoteIdentityKey": "BQnX03z8PTpMSQlB4qIcVSbAtROuM4uMgFIi//iuD1Fe"
            },
            "_chains": {
              "BSfkp8QbwgKhGtz1dSkDCyL1TETNPQgckRMRCvtPpSpN": {
                "chainKey": {
                  "counter": 0,
                  "key": "iFEMMyYQx4xZPaFjD8lv0WGLMK8v3WqwDXEReTPWtoI="
                },
                "chainType": 2,
                "messageKeys": {}
              },
              "BfTiguoDvbb3I6CrLJo+aOtoFLIFsRs8k3Ii/t6Fk2la": {
                "chainKey": {
                  "counter": -1,
                  "key": "bSSVzu5vEmxHdVODsNIEjxP8Di5ivmy8NCFpL8FgNuM="
                },
                "chainType": 1,
                "messageKeys": {}
              }
            }
          }
        },
        "version": "v1"
      },
      "6285795897037.0": {
        "_sessions": {
          "BepWVyd57wyrm6WgNu6PGe6vuwWiL2LpaBIU4M1q1Chf": {
            "registrationId": 1852087531,
            "currentRatchet": {
              "ephemeralKeyPair": {
                "pubKey": "BVhelqnLRF3KQ9qHWf5Iasa/nMY5jme5obP3VCMq+bkm",
                "privKey": "gPH/MBbAKvF1T402alJFMmYKfeW+id0Ie+Vh1l4fd2s="
              },
              "lastRemoteEphemeralKey": "BUkrq6bFXtsqQ//VR4MtPgkADfIeHoyhwk5VsOeIEY8g",
              "previousCounter": 0,
              "rootKey": "e+6jS2JnPg49kF+wsXJwMeewEuQVaNQsxrODUv8efGM="
            },
            "indexInfo": {
              "baseKey": "BepWVyd57wyrm6WgNu6PGe6vuwWiL2LpaBIU4M1q1Chf",
              "baseKeyType": 2,
              "closed": -1,
              "used": 1669609324945,
              "created": 1669609324945,
              "remoteIdentityKey": "BRVknRdGnq4egjD6BfnQ5ILPOL2Kr3BJjuQdTdKTxgMT"
            },
            "_chains": {
              "BUkrq6bFXtsqQ//VR4MtPgkADfIeHoyhwk5VsOeIEY8g": {
                "chainKey": {
                  "counter": 0,
                  "key": "EQd6vQi/x9BEfBZw20rJNKG0Ayusd1MeM4XEYCToPoI="
                },
                "chainType": 2,
                "messageKeys": {}
              },
              "BVhelqnLRF3KQ9qHWf5Iasa/nMY5jme5obP3VCMq+bkm": {
                "chainKey": {
                  "counter": -1,
                  "key": "wc8wOUw/kM/eAyQVGrltwvHrdyhggQYsgy5j0fIGLek="
                },
                "chainType": 1,
                "messageKeys": {}
              }
            }
          }
        },
        "version": "v1"
      },
      "6283809517252.0": {
        "_sessions": {
          "BQx5x4ek/MBRdz42g6WFBM27vTMMAW3KGMB6bRLZefgk": {
            "registrationId": 1197747481,
            "currentRatchet": {
              "ephemeralKeyPair": {
                "pubKey": "BaUsOmO0/ryLQuSqmga/oeqDzmROARg1dWqXMl6PEC5O",
                "privKey": "SE/WlTSpOtBHIp3RAzqj2Z16QaX6dbvBgYUnc0U+yn4="
              },
              "lastRemoteEphemeralKey": "BcCRCiO8okQQlWO+QFD2FD3xDynXg4YYGhFNampuxp1j",
              "previousCounter": 0,
              "rootKey": "VMrzEKoyTq2STPWMnu0ZjP9MUbIuwrPufm1skvzYdWo="
            },
            "indexInfo": {
              "baseKey": "BQx5x4ek/MBRdz42g6WFBM27vTMMAW3KGMB6bRLZefgk",
              "baseKeyType": 2,
              "closed": -1,
              "used": 1669609388141,
              "created": 1669609388140,
              "remoteIdentityKey": "BVX1qpekWgIcvg0BGO31dEGb4WkbWQV/i1mYwUSU09MJ"
            },
            "_chains": {
              "BcCRCiO8okQQlWO+QFD2FD3xDynXg4YYGhFNampuxp1j": {
                "chainKey": {
                  "counter": 0,
                  "key": "nE8+zeQGW+BV8Xf0nMEq0zqzHsFLtqCPSHMjz9Itxk8="
                },
                "chainType": 2,
                "messageKeys": {}
              },
              "BaUsOmO0/ryLQuSqmga/oeqDzmROARg1dWqXMl6PEC5O": {
                "chainKey": {
                  "counter": -1,
                  "key": "A/wuxvk2eL5X58eswckHAId60ewbM4CWLxpK9+FhJbs="
                },
                "chainType": 1,
                "messageKeys": {}
              }
            }
          }
        },
        "version": "v1"
      },
      "6285789430723.0": {
        "_sessions": {
          "BQIWN7cfGlTyxbJ59R2duoz0vhjoQKo+8LSFGMRI8D0i": {
            "registrationId": 1791953139,
            "currentRatchet": {
              "ephemeralKeyPair": {
                "pubKey": "BSbnxzVgoqMjFUwTyMOjz5ZBVm4yyYFwk6pmW/zujmoX",
                "privKey": "qKa73TFovgxk5RLwk+gVUNCcJYPDvYRgSJ7WgK5wMEk="
              },
              "lastRemoteEphemeralKey": "BbSQ068wWdqww94fJU9qW/eFRu+Sfuz9xKB5YmVh6fgA",
              "previousCounter": 0,
              "rootKey": "Cei8UssrEILpzHnjs0rReGBenZZFfQUWOLBghBY6jks="
            },
            "indexInfo": {
              "baseKey": "BQIWN7cfGlTyxbJ59R2duoz0vhjoQKo+8LSFGMRI8D0i",
              "baseKeyType": 2,
              "closed": -1,
              "used": 1669609542847,
              "created": 1669609542847,
              "remoteIdentityKey": "Bft3CHnK1uRsEiR4GeuY3VkHuOdZXRAcpeb3wNpcPx44"
            },
            "_chains": {
              "BbSQ068wWdqww94fJU9qW/eFRu+Sfuz9xKB5YmVh6fgA": {
                "chainKey": {
                  "counter": 0,
                  "key": "yUM8Gve5Dp2v99AeEyb+Dp847mJmTKLfFLmkFHNecy4="
                },
                "chainType": 2,
                "messageKeys": {}
              },
              "BSbnxzVgoqMjFUwTyMOjz5ZBVm4yyYFwk6pmW/zujmoX": {
                "chainKey": {
                  "counter": -1,
                  "key": "tD6doCzhuOCWLVHkPIFYyh4YyTOJ2FMduuD//7dJiWI="
                },
                "chainType": 1,
                "messageKeys": {}
              }
            }
          }
        },
        "version": "v1"
      },
      "62895358628600:1.0": {
        "_sessions": {
          "BdnndkX67VKZQd6/vdxD2+Y95QOjwVvENvZ5rEpCuFcx": {
            "registrationId": 9792,
            "currentRatchet": {
              "ephemeralKeyPair": {
                "pubKey": "BY+Si9vL/iMv5tRUiO+E8zfI9PqSnbM6s1CWJVSAgKd8",
                "privKey": "wCfuOfupQP3jl9O9mq+w0KeuQdO5eCrkLbj2GAnNuF4="
              },
              "lastRemoteEphemeralKey": "BXYXBmA6mM2Y2WukaO+RTb6ZPNarDw/48aWe42y+j9dC",
              "previousCounter": 0,
              "rootKey": "N920CRSietfPuRHJTt9xaLj4AyETL1NbIfYQ6MvNwZM="
            },
            "indexInfo": {
              "baseKey": "BdnndkX67VKZQd6/vdxD2+Y95QOjwVvENvZ5rEpCuFcx",
              "baseKeyType": 1,
              "closed": -1,
              "used": 1669609914927,
              "created": 1669609914927,
              "remoteIdentityKey": "BdM6TapNBvHvSFfIEIUeYhzLrO/B/bCRkG+GlVrFrpdP"
            },
            "_chains": {
              "BY+Si9vL/iMv5tRUiO+E8zfI9PqSnbM6s1CWJVSAgKd8": {
                "chainKey": {
                  "counter": 0,
                  "key": "6cwTZIeokyIPGYVIsf+5HrXly048zpJkVIbitIVizgs="
                },
                "chainType": 1,
                "messageKeys": {}
              }
            },
            "pendingPreKey": {
              "signedKeyId": 1,
              "baseKey": "BdnndkX67VKZQd6/vdxD2+Y95QOjwVvENvZ5rEpCuFcx",
              "preKeyId": 60
            }
          }
        },
        "version": "v1"
      },
      "6281219794647.0": {
        "_sessions": {
          "BaFlZn8fNRvM4OtaublnustnykUGmanhQSF3n6IWKTd0": {
            "registrationId": 2011850628,
            "currentRatchet": {
              "ephemeralKeyPair": {
                "pubKey": "BQylNnyS1O18N9r8Kd2vWA/Gldx7/8ohkcs7L6jydsMs",
                "privKey": "IFeucBer/2z3LpoZ/usLUfDiHRgiIENVeDO7huHyEE0="
              },
              "lastRemoteEphemeralKey": "BaHH6Ii3m0v0M8bds8rUgwgEaXL49Oa8D8qwW/iu431M",
              "previousCounter": 0,
              "rootKey": "2Om8MrRUPZtIv76PvdIRV7dVrF7z2IzxBHgORI9ots8="
            },
            "indexInfo": {
              "baseKey": "BaFlZn8fNRvM4OtaublnustnykUGmanhQSF3n6IWKTd0",
              "baseKeyType": 1,
              "closed": -1,
              "used": 1669609914946,
              "created": 1669609914946,
              "remoteIdentityKey": "BTtVOec3X6l9kms5rHOoZiPKZ5nJFzkQ2XNfk5SzXtFk"
            },
            "_chains": {
              "BQylNnyS1O18N9r8Kd2vWA/Gldx7/8ohkcs7L6jydsMs": {
                "chainKey": {
                  "counter": 0,
                  "key": "VnCqAODzIDwDda5uQZ0jptg8OEgW5dO6IA29nuzD2n4="
                },
                "chainType": 1,
                "messageKeys": {}
              }
            },
            "pendingPreKey": {
              "signedKeyId": 0,
              "baseKey": "BaFlZn8fNRvM4OtaublnustnykUGmanhQSF3n6IWKTd0",
              "preKeyId": 3527454
            }
          }
        },
        "version": "v1"
      },
      "6281221882891.0": {
        "_sessions": {
          "BfGE6x33rVr11kESETetzQk3jjork9Msif3JtAf7IFAu": {
            "registrationId": 1425738914,
            "currentRatchet": {
              "ephemeralKeyPair": {
                "pubKey": "BXY8o1HWdQm4EYc+lBJFep4qxJN093I57NlxzSdvnh9N",
                "privKey": "gOS8QdBc/BWZ9/GTEelfp3kZ2q2TPQuA1JZxtlWTwFo="
              },
              "lastRemoteEphemeralKey": "BagSnO4JhRmBuEqQZZ915gMQq/U2+aT1PRJku4G7z7wU",
              "previousCounter": 0,
              "rootKey": "rTN6hi8Sd8ORXq113AlCYPJWx6LpRV4NsNHCNz6+2lI="
            },
            "indexInfo": {
              "baseKey": "BfGE6x33rVr11kESETetzQk3jjork9Msif3JtAf7IFAu",
              "baseKeyType": 1,
              "closed": -1,
              "used": 1669609914965,
              "created": 1669609914965,
              "remoteIdentityKey": "BVrStKlIsm1OwgEymnxL6PMjQ0DrOvuFJEQDD7t6ffxN"
            },
            "_chains": {
              "BXY8o1HWdQm4EYc+lBJFep4qxJN093I57NlxzSdvnh9N": {
                "chainKey": {
                  "counter": 0,
                  "key": "LXKZol0ZohKI1YQWpEDNgMMRF8kwURWMXKUhxD+jqcQ="
                },
                "chainType": 1,
                "messageKeys": {}
              }
            },
            "pendingPreKey": {
              "signedKeyId": 6,
              "baseKey": "BfGE6x33rVr11kESETetzQk3jjork9Msif3JtAf7IFAu",
              "preKeyId": 6501415
            }
          }
        },
        "version": "v1"
      },
      "6281572370195.0": {
        "_sessions": {
          "BWCZfVDR5kNXcnPIOYF/nof8WczwrTAV2vSVVNIv3rtL": {
            "registrationId": 1257292370,
            "currentRatchet": {
              "ephemeralKeyPair": {
                "pubKey": "Be5oC4CbAukq4K3PoJsWpY5WidLdZwQong7Ulu3rGI0x",
                "privKey": "qELSSSen/SdYDzmLfYHTfmjd+B1LWUEpPfLm+5F0AEY="
              },
              "lastRemoteEphemeralKey": "BXtNWz5xJ7bu6j0s/MoGoqxvEu6TGVrZ9kyFDAIlpt9b",
              "previousCounter": 0,
              "rootKey": "kLCruigLXNwn9XXjKELjSHG/1OqVynvqyWtwcMzt+B8="
            },
            "indexInfo": {
              "baseKey": "BWCZfVDR5kNXcnPIOYF/nof8WczwrTAV2vSVVNIv3rtL",
              "baseKeyType": 1,
              "closed": -1,
              "used": 1669609914984,
              "created": 1669609914984,
              "remoteIdentityKey": "BdeJGoJw3aHpzBpRTBImTIJuxJnNv5UuVqmLYDXTcTZp"
            },
            "_chains": {
              "Be5oC4CbAukq4K3PoJsWpY5WidLdZwQong7Ulu3rGI0x": {
                "chainKey": {
                  "counter": 0,
                  "key": "rZh3JTdLYw0UJ205JVmBpqgwlCCZQAuiYYtdTrGQl1U="
                },
                "chainType": 1,
                "messageKeys": {}
              }
            },
            "pendingPreKey": {
              "signedKeyId": 7,
              "baseKey": "BWCZfVDR5kNXcnPIOYF/nof8WczwrTAV2vSVVNIv3rtL",
              "preKeyId": 3372217
            }
          }
        },
        "version": "v1"
      },
      "6283170982391.0": {
        "_sessions": {
          "BcdFlLMoNqsc/IvCU5kkdGYIYUH5XkqUPeRJhqi3ZHJg": {
            "registrationId": 787093922,
            "currentRatchet": {
              "ephemeralKeyPair": {
                "pubKey": "BQSy4A1Aae3ot/DAcKguf8IOqVzXSxJnsbYfGOS6gFdO",
                "privKey": "UF3yDGldKJjMkAJUn0V4pFU2f0BNLAkhdM0Q6NxzUl0="
              },
              "lastRemoteEphemeralKey": "BRSZde+Vj/By8MI7+9YsykAN8qF/hOiTeKvAEYMMQXEJ",
              "previousCounter": 0,
              "rootKey": "KEhpuprOpwEmXylTbHXbYQ/6WCFFZRUsk5/TwuDmAI8="
            },
            "indexInfo": {
              "baseKey": "BcdFlLMoNqsc/IvCU5kkdGYIYUH5XkqUPeRJhqi3ZHJg",
              "baseKeyType": 1,
              "closed": -1,
              "used": 1669609915004,
              "created": 1669609915004,
              "remoteIdentityKey": "BS1xSJzS3eCga/HRvbENT4nTiQ977tAtQlQ1lpkJz44F"
            },
            "_chains": {
              "BQSy4A1Aae3ot/DAcKguf8IOqVzXSxJnsbYfGOS6gFdO": {
                "chainKey": {
                  "counter": 0,
                  "key": "lh2juYxeY5xcB7K5WYab/22Uwq4Qzukthxr/HPV34ac="
                },
                "chainType": 1,
                "messageKeys": {}
              }
            },
            "pendingPreKey": {
              "signedKeyId": 9,
              "baseKey": "BcdFlLMoNqsc/IvCU5kkdGYIYUH5XkqUPeRJhqi3ZHJg",
              "preKeyId": 8300952
            }
          }
        },
        "version": "v1"
      },
      "62895358628600.0": {
        "_sessions": {
          "BTZ14rt7aixILSiBb5IinJdiaVZElMhn33PA4RCdW/5B": {
            "registrationId": 1128130535,
            "currentRatchet": {
              "ephemeralKeyPair": {
                "pubKey": "BVpg4L6Zuee6PQE/8tKejqblisyaYYnEzMeeKA7cPywx",
                "privKey": "iFGY97Iuvy30hxDxQxS+giIob/mrszJAViNlA/wcvF4="
              },
              "lastRemoteEphemeralKey": "Bdq01ZdQwXliT1NouT48pQAaC5ufb39m2dOrDWo5ksJ8",
              "previousCounter": 0,
              "rootKey": "jz5WOUdewkjmHIoI4qDMHIvevWCM+OHsscpIwNawPl4="
            },
            "indexInfo": {
              "baseKey": "BTZ14rt7aixILSiBb5IinJdiaVZElMhn33PA4RCdW/5B",
              "baseKeyType": 1,
              "closed": -1,
              "used": 1669609915023,
              "created": 1669609915023,
              "remoteIdentityKey": "BekUS9YFjruT9T6VJDh7m8I46/aHZqnJItvqxu6jZnsS"
            },
            "_chains": {
              "BVpg4L6Zuee6PQE/8tKejqblisyaYYnEzMeeKA7cPywx": {
                "chainKey": {
                  "counter": 0,
                  "key": "Bt4b9cbXSXd+iIQFAhvWyUyCRZ+94xqjnRTjAOf4/2w="
                },
                "chainType": 1,
                "messageKeys": {}
              }
            },
            "pendingPreKey": {
              "signedKeyId": 1,
              "baseKey": "BTZ14rt7aixILSiBb5IinJdiaVZElMhn33PA4RCdW/5B",
              "preKeyId": 9713295
            }
          }
        },
        "version": "v1"
      },
      "6289677442660.0": {
        "_sessions": {
          "BfMsuwdfr2Prh5VT0B2ae2JOTnMzDJ7NNZNxKWCagoxT": {
            "registrationId": 1253782879,
            "currentRatchet": {
              "ephemeralKeyPair": {
                "pubKey": "BZJzL0KG1fMe+1SfigOqJU6nYtRTHfxgNelYmutHIzhe",
                "privKey": "QPGO4JU/Shiji2WcmP0OUgIAWwRDFSb7uCz7f6l9bE0="
              },
              "lastRemoteEphemeralKey": "BbCvJsX5dM6iPR6sUDUjE1rTLv+TuKoKZden9VO4+FJK",
              "previousCounter": 0,
              "rootKey": "80oxaumkRNvb/xIygNtqSrRErc+dMQgrcP47x8V9qtU="
            },
            "indexInfo": {
              "baseKey": "BfMsuwdfr2Prh5VT0B2ae2JOTnMzDJ7NNZNxKWCagoxT",
              "baseKeyType": 1,
              "closed": -1,
              "used": 1669609915041,
              "created": 1669609915041,
              "remoteIdentityKey": "BVRcUACNmGD2PsGeA7YVt+NyNXfvnH0qyiY9xYVGMWcl"
            },
            "_chains": {
              "BZJzL0KG1fMe+1SfigOqJU6nYtRTHfxgNelYmutHIzhe": {
                "chainKey": {
                  "counter": 0,
                  "key": "pqtBMFQ5yrdwDd/GUDgppz0rz0hrR5DLhnWmfD4xxJY="
                },
                "chainType": 1,
                "messageKeys": {}
              }
            },
            "pendingPreKey": {
              "signedKeyId": 12,
              "baseKey": "BfMsuwdfr2Prh5VT0B2ae2JOTnMzDJ7NNZNxKWCagoxT",
              "preKeyId": 6786974
            }
          }
        },
        "version": "v1"
      },
      "6283116512556.0": {
        "_sessions": {
          "BdsxRk/23x8fNn9wPa4MG1s7m3lkVbSOgHQVNC1Wb29H": {
            "registrationId": 1807476633,
            "currentRatchet": {
              "ephemeralKeyPair": {
                "pubKey": "BX6ZWCbVTdlJ/xUUzXDrmDJJ7Bv75U6YBIxsY+cYgFxr",
                "privKey": "eDrsJa4GaS2VK5Pg6JSDqsxjqP5deKGgEhbnB6J5km8="
              },
              "lastRemoteEphemeralKey": "BSs19pt5p8W2uSiyi1+dLd67Az2r07a19aLPCebebpAR",
              "previousCounter": 0,
              "rootKey": "sKIMylnPEdFf2vE9XhJI2YE/P+aDutvfFLHVCPwIxHg="
            },
            "indexInfo": {
              "baseKey": "BdsxRk/23x8fNn9wPa4MG1s7m3lkVbSOgHQVNC1Wb29H",
              "baseKeyType": 2,
              "closed": -1,
              "used": 1669609947451,
              "created": 1669609947451,
              "remoteIdentityKey": "BV6jrf/FzAiwv9QNu2FPg9UbbOgiu4yV7rjW5CkTjs5s"
            },
            "_chains": {
              "BSs19pt5p8W2uSiyi1+dLd67Az2r07a19aLPCebebpAR": {
                "chainKey": {
                  "counter": 0,
                  "key": "I/t4ukzXBdEk743AYwAGzh8rG1YjKa6R1e5nNdzcF00="
                },
                "chainType": 2,
                "messageKeys": {}
              },
              "BX6ZWCbVTdlJ/xUUzXDrmDJJ7Bv75U6YBIxsY+cYgFxr": {
                "chainKey": {
                  "counter": -1,
                  "key": "pSIuq+mwbfCIR7PihdV6d7F4XTKtkNgJb9/PWmRVRoI="
                },
                "chainType": 1,
                "messageKeys": {}
              }
            }
          }
        },
        "version": "v1"
      },
      "6283837135145.0": {
        "_sessions": {
          "BavstqopATqEbEK+J867MsssV/5EQQO/ARho6qsvr9ZP": {
            "registrationId": 821305165,
            "currentRatchet": {
              "ephemeralKeyPair": {
                "pubKey": "BRVrudGt83uEiRDTMZvRwOPxL63nZdZaD1hYj5IyDIJF",
                "privKey": "kPAEBryEW1hEnHhBGryI+nwWcP4jpiKR1q4PzqHJbVQ="
              },
              "lastRemoteEphemeralKey": "BcEKm1vHV/h4w6R0JiP+SEPBUITgQ9yuBxckizl+QWBY",
              "previousCounter": 0,
              "rootKey": "axAsGkmEWwZffxX/G7r64tF73qxOpPbyq1fUA3eWxQw="
            },
            "indexInfo": {
              "baseKey": "BavstqopATqEbEK+J867MsssV/5EQQO/ARho6qsvr9ZP",
              "baseKeyType": 2,
              "closed": -1,
              "used": 1669609981763,
              "created": 1669609981763,
              "remoteIdentityKey": "BUcx/y+/r8ors10t54Ym3kASmkqccG02IVC6BL0NkS8C"
            },
            "_chains": {
              "BcEKm1vHV/h4w6R0JiP+SEPBUITgQ9yuBxckizl+QWBY": {
                "chainKey": {
                  "counter": 3,
                  "key": "TjULrNDgcLcyEkOvDPBjATjzfdELxED/mPElEne1PH4="
                },
                "chainType": 2,
                "messageKeys": {
                  "0": "Fea2yyYwX24ZPXMONZVvUdH/xp5/2K33VI+bFk6LpMs="
                }
              },
              "BRVrudGt83uEiRDTMZvRwOPxL63nZdZaD1hYj5IyDIJF": {
                "chainKey": {
                  "counter": -1,
                  "key": "50OlBGH3Mq4bStjMW1ROFp2iEt3J3I+C0TfXElOfJTk="
                },
                "chainType": 1,
                "messageKeys": {}
              }
            }
          }
        },
        "version": "v1"
      },
      "6285747592371.0": {
        "_sessions": {
          "BY/V/VcF/oxagSvgtB66VVrr0LRSQSwf/7LoUIUQ0iVr": {
            "registrationId": 539550373,
            "currentRatchet": {
              "ephemeralKeyPair": {
                "pubKey": "Ba6D44BaJusC52KRf4kPR1Hsh5Z5JXLAGGjQgpdrH+F1",
                "privKey": "QLZv0wYiVnFe24ulORlvPnvtz2BKb46qrPpF6OMJU2s="
              },
              "lastRemoteEphemeralKey": "BdeDR5BePykrQZzeZ6MF3EI9gUbDnMkCA5r082mp1Et+",
              "previousCounter": 0,
              "rootKey": "AUJ/bDzWWZ6YfXe1UFP7A+5AngvrdbaFf5HTtOeXslY="
            },
            "indexInfo": {
              "baseKey": "BY/V/VcF/oxagSvgtB66VVrr0LRSQSwf/7LoUIUQ0iVr",
              "baseKeyType": 2,
              "closed": -1,
              "used": 1669610187967,
              "created": 1669610187967,
              "remoteIdentityKey": "Bffm/eOV6uWQfXvkpWTKeVNSRtx1p7ea+xw6Akzo0klQ"
            },
            "_chains": {
              "BdeDR5BePykrQZzeZ6MF3EI9gUbDnMkCA5r082mp1Et+": {
                "chainKey": {
                  "counter": 0,
                  "key": "LBopC117S2CuOsKY1Am3P5fp2ALo1ecSwiWu0szxmy0="
                },
                "chainType": 2,
                "messageKeys": {}
              },
              "Ba6D44BaJusC52KRf4kPR1Hsh5Z5JXLAGGjQgpdrH+F1": {
                "chainKey": {
                  "counter": -1,
                  "key": "IAAFvtv7k/qvBbIyjbX15lNHhVE+1t37OpXeHmTTJm8="
                },
                "chainType": 1,
                "messageKeys": {}
              }
            }
          }
        },
        "version": "v1"
      },
      "6285702236360.0": {
        "_sessions": {
          "BSHgbpNb7cn3PaIF3In1Qhs+Q2AvKqj0ZMwKqFoR3xMn": {
            "registrationId": 914341092,
            "currentRatchet": {
              "ephemeralKeyPair": {
                "pubKey": "BXvUOT1Slf6Xb4rsgn+RL02AJ1YD9/6GC79kl1720GdK",
                "privKey": "eB/tEj2zfteqCJx+EbQERFgn3lKEbDkVV38hiDPcym4="
              },
              "lastRemoteEphemeralKey": "BTU7BFVhOm6Bq8m08FapGK+4FBo6uTFWGsQKJXfFLIEY",
              "previousCounter": 0,
              "rootKey": "WBgjBZiAwhl/gfjupMP1lIncbz99Rbrg6yCV+ot8Cjs="
            },
            "indexInfo": {
              "baseKey": "BSHgbpNb7cn3PaIF3In1Qhs+Q2AvKqj0ZMwKqFoR3xMn",
              "baseKeyType": 2,
              "closed": -1,
              "used": 1669610227890,
              "created": 1669610227890,
              "remoteIdentityKey": "BeVA0gIibJzSkUwKH36O8ls2ps/gxqs5XPQVo4OCe88h"
            },
            "_chains": {
              "BTU7BFVhOm6Bq8m08FapGK+4FBo6uTFWGsQKJXfFLIEY": {
                "chainKey": {
                  "counter": 0,
                  "key": "Z3zURpbr4sG60RPegcFVilHmsGDR9BBkAvoSmrh/orM="
                },
                "chainType": 2,
                "messageKeys": {}
              },
              "BXvUOT1Slf6Xb4rsgn+RL02AJ1YD9/6GC79kl1720GdK": {
                "chainKey": {
                  "counter": -1,
                  "key": "SvLiUdXAjP6GuqHlZklhwNdU9rdXe+vlTpD7PvFdLYM="
                },
                "chainType": 1,
                "messageKeys": {}
              }
            }
          }
        },
        "version": "v1"
      },
      "6283179883921.0": {
        "_sessions": {
          "BbyoOURCMppG2wLKyPJ5//fOH4lLbQKFj2W1A8TVdC0S": {
            "registrationId": 1224288570,
            "currentRatchet": {
              "ephemeralKeyPair": {
                "pubKey": "BTMfK8BYyMQ33IYuB59kQbnRtUWmJFsaTYpuVYCHV1gJ",
                "privKey": "kHPJP+CaMYFXOZRtWP+yuY2ChMEEuFYa+079PjY97nY="
              },
              "lastRemoteEphemeralKey": "BT9oKeF6ElHf//zp/As6zupjLxSpMoDdc+KmBs4TRmxX",
              "previousCounter": 0,
              "rootKey": "II+asrc9bcV6tDdmnhhd3OVXWP1c7hkyS3eldKcc65M="
            },
            "indexInfo": {
              "baseKey": "BbyoOURCMppG2wLKyPJ5//fOH4lLbQKFj2W1A8TVdC0S",
              "baseKeyType": 2,
              "closed": -1,
              "used": 1669610723630,
              "created": 1669610723630,
              "remoteIdentityKey": "BZYn0KYv4bs+3hzyKfNqRMRvL28GrvB8jy7vRqgNtn0r"
            },
            "_chains": {
              "BT9oKeF6ElHf//zp/As6zupjLxSpMoDdc+KmBs4TRmxX": {
                "chainKey": {
                  "counter": 0,
                  "key": "3v0F6P9XuGBvs7DawrmsNrW/Lb+Uv1fK5iz2BcHAajU="
                },
                "chainType": 2,
                "messageKeys": {}
              },
              "BTMfK8BYyMQ33IYuB59kQbnRtUWmJFsaTYpuVYCHV1gJ": {
                "chainKey": {
                  "counter": -1,
                  "key": "3K0mDNfs2i/alCVf9XOoahL1zNXFgiX/DSoWFP19xl8="
                },
                "chainType": 1,
                "messageKeys": {}
              }
            }
          }
        },
        "version": "v1"
      },
      "6285822094852.0": {
        "_sessions": {
          "BbXLPNCXIt2Q4Y3Q2TZzKxz7oI0YsCgs7SJ3IRMVtqo5": {
            "registrationId": 1421390355,
            "currentRatchet": {
              "ephemeralKeyPair": {
                "pubKey": "BctWT9ZEPuD/mRbCl0vqiF3Gm3v9qsJ2JH08MMjHfsZW",
                "privKey": "EEdwyUWdUMdxwChScFEaQoTZSyks2vuU1BZUj1W3iUA="
              },
              "lastRemoteEphemeralKey": "BbeAOPX23TbkcvkjAUioLHzawEqg/EHC1yWPjw4Qr39b",
              "previousCounter": 0,
              "rootKey": "6xex685/7YSvaFKXAONBQ60264OmJbL7WhDhOkbSK0U="
            },
            "indexInfo": {
              "baseKey": "BbXLPNCXIt2Q4Y3Q2TZzKxz7oI0YsCgs7SJ3IRMVtqo5",
              "baseKeyType": 2,
              "closed": -1,
              "used": 1669610768288,
              "created": 1669610768288,
              "remoteIdentityKey": "BZte0jQxHRjp2tpFMVV/dtotbnnjLx8MfjiZCB2+l7oP"
            },
            "_chains": {
              "BbeAOPX23TbkcvkjAUioLHzawEqg/EHC1yWPjw4Qr39b": {
                "chainKey": {
                  "counter": 0,
                  "key": "2Zr8G/RFdxbyn5m5FIZgt2eK8om6/oaBxbmMyWd66VY="
                },
                "chainType": 2,
                "messageKeys": {}
              },
              "BctWT9ZEPuD/mRbCl0vqiF3Gm3v9qsJ2JH08MMjHfsZW": {
                "chainKey": {
                  "counter": -1,
                  "key": "/pTaNZMl6e/gO1pjjGoBe9eGkrRKx1lrHH9eewtIbwI="
                },
                "chainType": 1,
                "messageKeys": {}
              }
            }
          }
        },
        "version": "v1"
      }
    },
    "appStateSyncKeys": {
      "AAAAAPGS": {
        "keyData": "zoWApsLvRjGIPuomcMTEare9UJ+g8N4A8NEgTlV+h4o=",
        "fingerprint": {
          "rawId": 1084598579,
          "currentIndex": 1,
          "deviceIndexes": [
            0,
            1
          ]
        },
        "timestamp": "1669608315450"
      }
    },
    "appStateVersions": {
      "critical_block": {
        "version": 1,
        "hash": {
          "type": "Buffer",
          "data": "RfdcPv+N32k1qhZ2sr62i/BeQaqB+UYc/nl8wldHA1pqRWvHEm9MeMqX7I2rZfdC97CdFEpywDrJ2fQqgxlSY8nTsY5BblIVYz8O9/6eEjaARSzPbRJ/vV3IJWfiJkkOIOfQiTmhQf+RNuyFR5F5tF4Jk9uuu7Ji+f4Q73hAN5w="
        },
        "indexValueMap": {
          "HDIXJkW0e+eNH4J3Xv8wpJHcSJEMd8m3+6VuiZjrt5I=": {
            "valueMac": {
              "type": "Buffer",
              "data": "uZ0UL/8vVvogruYtObGodCHr+QMBw47nXCAhuE1LqMQ="
            }
          },
          "us0hBcKRjvteiwkbrUBM0KvG+utRRX+BQAg9tXRsUOA=": {
            "valueMac": {
              "type": "Buffer",
              "data": "/kK+PgUpXgk8jj4cWkM4AJ/FSkhJqSUKQg+V3+A7QvE="
            }
          }
        }
      },
      "regular": {
        "version": 1,
        "hash": {
          "type": "Buffer",
          "data": "cCOOKjrIo/CMog4eBO/wGY/+EJlXDiAWhDfDAJ+DRT+Z4FC74lYshl3uriDRBKsZEvvjwKTc36b2VoHOnvWq8Z2Um9Ic35VWTZR/K+w+sph1PzURFl4ytDCL8ZYQqiTcs3zx/lGTaw16zcvv2JZYwVE3RppAMEs6uOv3d3sB32w="
        },
        "indexValueMap": {
          "/dtqaAz3w9EmceDj0BseOTlatrXRWJPtfj5HohaeV3o=": {
            "valueMac": {
              "type": "Buffer",
              "data": "gbizEG4jHAtMnWfgoMi8VGAOcQCkuwYQFP9oxTJgePU="
            }
          },
          "ZPzky6vOCPtSaNKs4Y3ceWuTUP9smhy0da4Sw37mj9A=": {
            "valueMac": {
              "type": "Buffer",
              "data": "oPmeY/aWcUDtsqXER4ys+nMmPzJ0aPW9qPwxK9QEI34="
            }
          },
          "LAouqDWPhUuJwA2WJoADP8GQTs5zmoMziNcX6qmQ9N0=": {
            "valueMac": {
              "type": "Buffer",
              "data": "YOKhZX85MtuBy9ssw97hulBcRHL8R874vO2b98TDmFw="
            }
          },
          "uNf6mH79+2khPvITMGTZoMnzFwiPEnxXlmmXhmRXqeY=": {
            "valueMac": {
              "type": "Buffer",
              "data": "iWxx+xTN3IFtFSp+z/T6mPo0T667BcAge+db9JqrHSY="
            }
          },
          "JcN0HzRKcRQo4msUp5d3f2sEoaoPVNqXFVVheMlwH28=": {
            "valueMac": {
              "type": "Buffer",
              "data": "C2dA29R3W3Kiyqah9FiImhLxfPurbMcX21XZCk2a6Og="
            }
          },
          "/sxyTlsXfniQ8Up0Yk0og9i2djHn4XzGAwrUEpPmtBY=": {
            "valueMac": {
              "type": "Buffer",
              "data": "FxpPUUc5Ad332YXHOtqb/2t+UcRfzqrkzjKnQ2DGztA="
            }
          },
          "lwWl27yOpUQPv4900lN/OlzauQuLMjYbM93HdafJ6so=": {
            "valueMac": {
              "type": "Buffer",
              "data": "Iz9J9UodozXg05/PYOj7ZO47KSxnTKxnqKs2FXaNfyQ="
            }
          }
        }
      }
    },
    "senderKeys": {
      "120363023487921585@g.us::6285215319934::0": [
        {
          "senderKeyId": 908119935,
          "senderChainKey": {
            "iteration": 535,
            "seed": "EEWhOJ4EStg7uJLX+m6y8fzTmcac3qE8MtI/wLLmlUw="
          },
          "senderSigningKey": {
            "public": "BXCFF+EvcUUkChDRgEhR3TaXjVEVazifdK6KW4n4wtEO"
          },
          "senderMessageKeys": [
            {},
            {}
          ]
        },
        {
          "senderKeyId": 908119935,
          "senderChainKey": {
            "iteration": 521,
            "seed": "siaONNmKHvbZz51kRFcjGXCNB9sLKKks0+iq3CuJpvo="
          },
          "senderSigningKey": {
            "public": "BXCFF+EvcUUkChDRgEhR3TaXjVEVazifdK6KW4n4wtEO"
          },
          "senderMessageKeys": []
        }
      ],
      "status@broadcast::6281253874123::0": [
        {
          "senderKeyId": 1776951994,
          "senderChainKey": {
            "iteration": 40,
            "seed": "iyDk9X5wRrXhyDKeEmX00SesV1xHCu3cZzIcsKcKatg="
          },
          "senderSigningKey": {
            "public": "BeuFL2wZZNVBxlopLP+Yyu1Ys5ZSwDwC+cf/sWfJ8yMb"
          },
          "senderMessageKeys": [
            {},
            {}
          ]
        }
      ],
      "status@broadcast::6285735868941::0": [
        {
          "senderKeyId": 342065160,
          "senderChainKey": {
            "iteration": 0,
            "seed": "sQbi7g/PPW4DzojzbCyKBoo6rQXHdNhpzyaUuPITZHQ="
          },
          "senderSigningKey": {
            "public": "BYiGWa1HrDZzGDjAbcah3i/ZAcTdZpin9QHvJq/DOY0+"
          }
        }
      ],
      "status@broadcast::6283149289769::0": [
        {
          "senderKeyId": 883097699,
          "senderChainKey": {
            "iteration": 17,
            "seed": "YvbxDg6NdszTxJWdEj4OmJKjdKgSLEYpk/71PPmFx2g="
          },
          "senderSigningKey": {
            "public": "BV5WLyNsxv7mPLY1yqui+rz/3JRYyTy+657n2z26wSQI"
          }
        }
      ],
      "status@broadcast::6283863467345::0": [
        {
          "senderKeyId": 1039574250,
          "senderChainKey": {
            "iteration": 3,
            "seed": "xLRb6R9gMrofIggyJuMCjXiSwAQ8Gudc9BdaNNTSH2U="
          },
          "senderSigningKey": {
            "public": "Be8vMFDib6k+CZK0m31NHVunGXvTEVvCTaGdb2hZ8P05"
          }
        }
      ],
      "status@broadcast::6281563167690::0": [
        {
          "senderKeyId": 758796527,
          "senderChainKey": {
            "iteration": 0,
            "seed": "8P9RJOM58dmAR5Hi/Woqag3Ooy2CHPK3NjgR6I06OZE="
          },
          "senderSigningKey": {
            "public": "Ba8WIamcW7IrtK29qPYUYhtmTF8ORFbgdX4NvrIWOIRk"
          }
        }
      ],
      "status@broadcast::6281220590183::0": [
        {
          "senderKeyId": 1027527105,
          "senderChainKey": {
            "iteration": 2,
            "seed": "6rn6PxVueZmtfV0/P1VpZWh2sbgaB8yTSFvzhivdZ40="
          },
          "senderSigningKey": {
            "public": "BVhmweV0CPqzI8Otf6x3rSg1oTRWoPN5GtXQCbuDo1Rh"
          }
        }
      ],
      "status@broadcast::6283151524041::0": [
        {
          "senderKeyId": 1745941211,
          "senderChainKey": {
            "iteration": 5,
            "seed": "4pOLPJgmVxfVkJ0DCx9VhRjWFqAeJKM3/fitdjYHdDs="
          },
          "senderSigningKey": {
            "public": "BadiH2aA+o7jC2txJ0Vkbu5QUqQNc57yfPT82KD4yCwm"
          }
        }
      ],
      "status@broadcast::6285940752001::0": [
        {
          "senderKeyId": 21458336,
          "senderChainKey": {
            "iteration": 8,
            "seed": "Np/POxHEXibQRvFzQubPilXWBVMUse/CHsJqUP74FOI="
          },
          "senderSigningKey": {
            "public": "BRux9LnkwVEAF1xvZLg0ixwArj9A7I2+0+k8R9n15bAy"
          },
          "senderMessageKeys": [
            {
              "iteration": 3,
              "seed": "hLpssSlTFuePX+gTX/Ays4C0GutVNKyE8l7GZYF56t8="
            }
          ]
        }
      ],
      "status@broadcast::6285795897037::0": [
        {
          "senderKeyId": 1627215950,
          "senderChainKey": {
            "iteration": 9,
            "seed": "eWes3w4Qwg4dU7bjZ4pZcRj70IpaEETjfpC4wJBHAbg="
          },
          "senderSigningKey": {
            "public": "BZuyeAUsDRwUTzsYZjYsJGk8EcmS3wz17BFFdRCPFRxa"
          }
        }
      ],
      "status@broadcast::6283809517252::0": [
        {
          "senderKeyId": 1448203133,
          "senderChainKey": {
            "iteration": 0,
            "seed": "RH2xqRapbYmPFwMisXIrVv/SKg8BRToLXO2KltGhZZs="
          },
          "senderSigningKey": {
            "public": "Bd344OvkiO5fLxqN/0BVfVIGauCa9OeWEQFK5kWm8Tol"
          }
        }
      ],
      "status@broadcast::6285789430723::0": [
        {
          "senderKeyId": 1080609339,
          "senderChainKey": {
            "iteration": 21,
            "seed": "IfEkM+yvNVb4m9qtwKkge/p/AoAK8iKanhVQ4dml5Mk="
          },
          "senderSigningKey": {
            "public": "BetEEhCArBky5UdVZ1SFRa8uxnxRvO5XGAfBW0dumsFw"
          }
        }
      ],
      "120363023487921585@g.us::6283197670126:3::0": [
        {
          "senderKeyId": 1703232751,
          "senderChainKey": {
            "iteration": 18,
            "seed": "007SYA96vj3x4+2cNVFDIb0VElblfmyvyQZwKDOh0Xc="
          },
          "senderSigningKey": {
            "public": "BVvNUuZyqKyjstVeRdqHEpSnttLM+D5AQQMOFBVx/Utr",
            "private": "4HczGcpzV3rIn7Fi/o/i7/pYWRS70DI1e8Y/IzqvfWU="
          },
          "senderMessageKeys": []
        }
      ],
      "status@broadcast::6283116512556::0": [
        {
          "senderKeyId": 258866029,
          "senderChainKey": {
            "iteration": 3,
            "seed": "pfjzZgUYFF/tT9pF/0TkJi5GZyK7cOWmFX2DdVvrWpk="
          },
          "senderSigningKey": {
            "public": "Bffe/jYHlW4r2rB2iOfngJn4hQcMwbvZ2TYKMddpmchF"
          }
        }
      ],
      "status@broadcast::6283837135145::0": [
        {
          "senderKeyId": 1322437700,
          "senderChainKey": {
            "iteration": 4,
            "seed": "dLWytHhh/yXt/tGrnsnnUL0K0I1TfPsLgPhOrKfRVEE="
          },
          "senderSigningKey": {
            "public": "Bf4hrm/aTIGlOKq2vKpsxX9e2BNl9efg/gAsQkOCL1th"
          }
        }
      ],
      "status@broadcast::6285747592371::0": [
        {
          "senderKeyId": 1391677113,
          "senderChainKey": {
            "iteration": 3,
            "seed": "CzPkG6DoGKvzVpborBRjChB/pvfL1O37uj65BDHZ9OI="
          },
          "senderSigningKey": {
            "public": "BSP88qOr//vdw1ZgsEYf3SIC5EJWwjsoJOSSF6gXEBxu"
          }
        }
      ],
      "status@broadcast::6285702236360::0": [
        {
          "senderKeyId": 255241056,
          "senderChainKey": {
            "iteration": 2,
            "seed": "8LUlYFExHncxV1pZRi8vst6t43+CyIU+0azk0blVJ6s="
          },
          "senderSigningKey": {
            "public": "BdtjQfPXkhHkf7Sx3OvM4vP45RL3+0v1LxQL+xbFrARh"
          }
        }
      ],
      "status@broadcast::6283179883921::0": [
        {
          "senderKeyId": 263286010,
          "senderChainKey": {
            "iteration": 3,
            "seed": "FbMh1i9zYdmFrhAryBN6Uqs5Db94SZ+gJOMLRumuqYU="
          },
          "senderSigningKey": {
            "public": "BVgiOQN+ZJXUJ+S4k4m2qUIlGWGsyF9bMFpUnsqxojUd"
          }
        }
      ],
      "status@broadcast::6285822094852::0": [
        {
          "senderKeyId": 1598548790,
          "senderChainKey": {
            "iteration": 13,
            "seed": "dfqGI/LnPOgT2TZefBkmPk7+buDEvJXxLb3uQ01WKBc="
          },
          "senderSigningKey": {
            "public": "BeCFEiinvVv3a5UgdTc2fW7bwojGYU+EDR7+Lm7xVPRM"
          }
        }
      ]
    },
    "senderKeyMemory": {
      "120363023487921585@g.us": {
        "6289677442660@s.whatsapp.net": true,
        "62895358628600@s.whatsapp.net": true,
        "62895358628600:1@s.whatsapp.net": true,
        "6285215319934@s.whatsapp.net": true,
        "6283197670126@s.whatsapp.net": true,
        "6283170982391@s.whatsapp.net": true,
        "6281572370195@s.whatsapp.net": true,
        "6281221882891@s.whatsapp.net": true,
        "6281219794647@s.whatsapp.net": true
      }
    }
  }
}